cmake2graph/__init__.py
cmake2graph/cli.py
cmake2graph-0.1.1.dist-info/licenses/LICENSE
cmake2graph-0.1.1.dist-info/METADATA
cmake2graph-0.1.1.dist-info/WHEEL
cmake2graph-0.1.1.dist-info/entry_points.txt
cmake2graph-0.1.1.dist-info/top_level.txt
cmake2graph-0.1.1.dist-info/RECORD
